pseudoflow/__init__.py
pseudoflow/libhpf.so
pseudoflow/python/__init__.py
pseudoflow/python/graph_wrapper.py
pseudoflow/python/hpf.py
pseudoflow-2022.12.0.dist-info/LICENSE.md
pseudoflow-2022.12.0.dist-info/METADATA
pseudoflow-2022.12.0.dist-info/WHEEL
pseudoflow-2022.12.0.dist-info/top_level.txt
pseudoflow-2022.12.0.dist-info/RECORD
