Metadata-Version: 2.1
Name: pseudoflow
Version: 2022.12.0
Summary: Pseudoflow algorithm for the parametric minimum cut problem.
Home-page: https://github.com/quic0/pseudoflow
Author: Quico Spaen
Author-email: qspaen@berkeley.edu
License: Non-commercial license. Not an open-source license.
Keywords: minimum cut,network flow,parametric
Classifier: Development Status :: 3 - Alpha
Classifier: Programming Language :: Python :: 3
License-File: LICENSE.md
